main/PSU.py
main/__init__.py
undersample-0.1.dist-info/METADATA
undersample-0.1.dist-info/WHEEL
undersample-0.1.dist-info/top_level.txt
undersample-0.1.dist-info/RECORD
