Metadata-Version: 2.1
Name: undersample
Version: 0.1
Summary: Python package for PSU method
Home-page: https://github.com/YongSeok-Jeon/undersample
Author: Yongseok Jeon
Author-email: yjeon@ncsu.edu
License: MIT
Requires-Python: >=3
